{
  "id": "d5-all",
  "title": "核心字彙與構詞．領域總複習",
  "term": null,
  "chapter": "總複習",
  "scope": "review",
  "officialCodes": "ENG-核心字彙與構詞",
  "runtime": {
    "generator": "questions.js",
    "function": "window.EXAM_ENGINE.generateQuiz",
    "questionCount": 8,
    "minutes": 20,
    "nonRepeatPolicy": "app.js stores recent quiz signatures in localStorage and re-rolls seed when a duplicate signature appears.",
    "taxonomySource": "No fine-grained taxonomy yet; falls back to unit-level generators."
  },
  "taxonomy": [],
  "units": [
    {
      "unitId": 17,
      "title": "核心字彙：日常生活與學校",
      "grade": 5,
      "domain": "核心字彙與構詞",
      "basic": {
        "purpose": "Drills confirm grammar rules, vocabulary meaning, and standard sentence patterns; all questions are multiple choice.",
        "difficultyRange": [
          1,
          3
        ],
        "templateSource": "quiz-taxonomy.js / u17 / template",
        "guardrails": [
          "Junior-high English scope only (12-year curriculum grammar sequence + 2000-word list).",
          "Sentences and distractors are generated by quiz-taxonomy.js templates; answers are computed from the same parameters.",
          "No constructed-response items: the official 英語（閱讀／聽力）exam is multiple choice only."
        ]
      }
    },
    {
      "unitId": 18,
      "title": "核心字彙：情緒、個性與人際",
      "grade": 5,
      "domain": "核心字彙與構詞",
      "basic": {
        "purpose": "Drills confirm grammar rules, vocabulary meaning, and standard sentence patterns; all questions are multiple choice.",
        "difficultyRange": [
          1,
          3
        ],
        "templateSource": "quiz-taxonomy.js / u18 / template",
        "guardrails": [
          "Junior-high English scope only (12-year curriculum grammar sequence + 2000-word list).",
          "Sentences and distractors are generated by quiz-taxonomy.js templates; answers are computed from the same parameters.",
          "No constructed-response items: the official 英語（閱讀／聽力）exam is multiple choice only."
        ]
      }
    },
    {
      "unitId": 19,
      "title": "核心字彙：科技、環境與健康",
      "grade": 5,
      "domain": "核心字彙與構詞",
      "basic": {
        "purpose": "Drills confirm grammar rules, vocabulary meaning, and standard sentence patterns; all questions are multiple choice.",
        "difficultyRange": [
          1,
          3
        ],
        "templateSource": "quiz-taxonomy.js / u19 / template",
        "guardrails": [
          "Junior-high English scope only (12-year curriculum grammar sequence + 2000-word list).",
          "Sentences and distractors are generated by quiz-taxonomy.js templates; answers are computed from the same parameters.",
          "No constructed-response items: the official 英語（閱讀／聽力）exam is multiple choice only."
        ]
      }
    },
    {
      "unitId": 20,
      "title": "字彙猜測技巧與構詞法",
      "grade": 5,
      "domain": "核心字彙與構詞",
      "basic": {
        "purpose": "Drills confirm grammar rules, vocabulary meaning, and standard sentence patterns; all questions are multiple choice.",
        "difficultyRange": [
          1,
          3
        ],
        "templateSource": "quiz-taxonomy.js / u20 / template",
        "guardrails": [
          "Junior-high English scope only (12-year curriculum grammar sequence + 2000-word list).",
          "Sentences and distractors are generated by quiz-taxonomy.js templates; answers are computed from the same parameters.",
          "No constructed-response items: the official 英語（閱讀／聽力）exam is multiple choice only."
        ]
      }
    }
  ]
}
